json_strong_typing-0.4.1.dist-info/licenses/LICENSE
strong_typing/__init__.py
strong_typing/auxiliary.py
strong_typing/classdef.py
strong_typing/core.py
strong_typing/deserializer.py
strong_typing/docstring.py
strong_typing/exception.py
strong_typing/inspection.py
strong_typing/mapping.py
strong_typing/name.py
strong_typing/py.typed
strong_typing/schema.py
strong_typing/serialization.py
strong_typing/serializer.py
strong_typing/slots.py
strong_typing/topological.py
json_strong_typing-0.4.1.dist-info/METADATA
json_strong_typing-0.4.1.dist-info/WHEEL
json_strong_typing-0.4.1.dist-info/top_level.txt
json_strong_typing-0.4.1.dist-info/zip-safe
json_strong_typing-0.4.1.dist-info/RECORD
