Metadata-Version: 2.4
Name: json_strong_typing
Version: 0.4.1
Summary: Type-safe data interchange for Python data classes
Author-email: Levente Hunyadi <hunyadi@gmail.com>
Maintainer-email: Levente Hunyadi <hunyadi@gmail.com>
License-Expression: MIT
Project-URL: Homepage, https://github.com/hunyadi/strong_typing
Project-URL: Source, https://github.com/hunyadi/strong_typing
Keywords: json-schema,json-parsing,json-serialization,docstring-documentation,type-inspection
Classifier: Development Status :: 5 - Production/Stable
Classifier: Intended Audience :: Developers
Classifier: Operating System :: OS Independent
Classifier: Programming Language :: Python :: 3
Classifier: Programming Language :: Python :: 3.9
Classifier: Programming Language :: Python :: 3.10
Classifier: Programming Language :: Python :: 3.11
Classifier: Programming Language :: Python :: 3.12
Classifier: Programming Language :: Python :: 3.13
Classifier: Programming Language :: Python :: 3 :: Only
Classifier: Topic :: File Formats :: JSON
Classifier: Topic :: File Formats :: JSON :: JSON Schema
Classifier: Topic :: Text Processing :: Markup :: reStructuredText
Classifier: Typing :: Typed
Requires-Python: >=3.9
License-File: LICENSE
Requires-Dist: jsonschema>=4.25
Requires-Dist: typing_extensions>=4.14; python_version < "3.11"
Provides-Extra: dev
Requires-Dist: build>=1.3; extra == "dev"
Requires-Dist: mypy>=1.18; extra == "dev"
Requires-Dist: ruff>=0.14; extra == "dev"
Dynamic: license-file
